IndigoPy/__init__.py
IndigoPy/GUI/Formal.py
IndigoPy/GUI/__init__.py
IndigoPy/Math/Funcmaker.py
IndigoPy/Math/__init__.py
IndigoPy/Math/coordinates.py
IndigoPy/Math/plot.py
IndigoPy/Protein/__init__.py
IndigoPy/Protein/pdb.py
IndigoPy-0.0.1a2.data/data/Doc/Math/Funcmaker.md
IndigoPy-0.0.1a2.data/data/Doc/Protein/pdb.md
IndigoPy-0.0.1a2.data/data/Doc/examples/newscreen.py
IndigoPy-0.0.1a2.dist-info/LICENSE
IndigoPy-0.0.1a2.dist-info/METADATA
IndigoPy-0.0.1a2.dist-info/WHEEL
IndigoPy-0.0.1a2.dist-info/top_level.txt
IndigoPy-0.0.1a2.dist-info/RECORD
