Metadata-Version: 2.1
Name: IndigoPy
Version: 0.0.1a2
Summary: Basic function is done
Home-page: https://github.com/IndigoMad/IndigoPy.git
Author: Indigo Mad
Author-email: indigomad@pku.edu.cn
License: UNKNOWN
Platform: UNKNOWN
Classifier: Development Status :: 3 - Alpha
Classifier: Programming Language :: Python :: 3
Classifier: License :: OSI Approved :: MIT License
Classifier: Operating System :: Microsoft :: Windows
Classifier: Operating System :: Unix
Requires-Python: >=3
Requires-Dist: numpy
Requires-Dist: scipy
Requires-Dist: matplotlib
